CHANGES.txt
README.txt
setup.py
docs/LICENSE.GPL
docs/LICENSE.txt
plone/__init__.py
plone.sequencebatch.egg-info/PKG-INFO
plone.sequencebatch.egg-info/SOURCES.txt
plone.sequencebatch.egg-info/dependency_links.txt
plone.sequencebatch.egg-info/namespace_packages.txt
plone.sequencebatch.egg-info/not-zip-safe
plone.sequencebatch.egg-info/requires.txt
plone.sequencebatch.egg-info/top_level.txt
plone/sequencebatch/__init__.py
plone/sequencebatch/batch.py
plone/sequencebatch/configure.zcml