Metadata-Version: 1.0
Name: plone.sequencebatch
Version: 1.0a1
Summary: Facilities for creating a batched sequence.
Home-page: http://pypi.python.org/pypi/plone.sequencebatch
Author: Plone Foundation
Author-email: plone-developers@lists.sourceforge.net
License: GPL
Keywords: Plone
Platform: UNKNOWN
Classifier: Framework :: Plone
Classifier: Framework :: Zope2
